MANIFEST.in
setup.cfg
setup.py
gskChat/__init__.py
gskChat/cli.py
gskChat/client.py
gskChat/cookies.py
gskChat/debug.py
gskChat/errors.py
gskChat/image.py
gskChat/models.py
gskChat/stubs.py
gskChat/typing.py
gskChat/version.py
gskChat/webdriver.py
gskChat.egg-info/PKG-INFO
gskChat.egg-info/SOURCES.txt
gskChat.egg-info/dependency_links.txt
gskChat.egg-info/entry_points.txt
gskChat.egg-info/requires.txt
gskChat.egg-info/top_level.txt
gskChat/Provider/Aura.py
gskChat/Provider/Bing.py
gskChat/Provider/BingCreateImages.py
gskChat/Provider/ChatForAi.py
gskChat/Provider/Chatgpt4Online.py
gskChat/Provider/ChatgptAi.py
gskChat/Provider/ChatgptFree.py
gskChat/Provider/ChatgptNext.py
gskChat/Provider/ChatgptX.py
gskChat/Provider/DeepInfra.py
gskChat/Provider/FlowGpt.py
gskChat/Provider/FreeChatgpt.py
gskChat/Provider/FreeGpt.py
gskChat/Provider/GeminiPro.py
gskChat/Provider/GeminiProChat.py
gskChat/Provider/GigaChat.py
gskChat/Provider/GptTalkRu.py
gskChat/Provider/HuggingChat.py
gskChat/Provider/HuggingFace.py
gskChat/Provider/Koala.py
gskChat/Provider/Liaobots.py
gskChat/Provider/Llama2.py
gskChat/Provider/PerplexityLabs.py
gskChat/Provider/Pi.py
gskChat/Provider/Vercel.py
gskChat/Provider/You.py
gskChat/Provider/__init__.py
gskChat/Provider/base_provider.py
gskChat/Provider/helper.py
gskChat/Provider/__pycache__/Aura.cpython-312.pyc
gskChat/Provider/__pycache__/Bing.cpython-312.pyc
gskChat/Provider/__pycache__/BingCreateImages.cpython-312.pyc
gskChat/Provider/__pycache__/ChatForAi.cpython-312.pyc
gskChat/Provider/__pycache__/Chatgpt4Online.cpython-312.pyc
gskChat/Provider/__pycache__/ChatgptAi.cpython-312.pyc
gskChat/Provider/__pycache__/ChatgptFree.cpython-312.pyc
gskChat/Provider/__pycache__/ChatgptNext.cpython-312.pyc
gskChat/Provider/__pycache__/ChatgptX.cpython-312.pyc
gskChat/Provider/__pycache__/DeepInfra.cpython-312.pyc
gskChat/Provider/__pycache__/FlowGpt.cpython-312.pyc
gskChat/Provider/__pycache__/FreeChatgpt.cpython-312.pyc
gskChat/Provider/__pycache__/FreeGpt.cpython-312.pyc
gskChat/Provider/__pycache__/GeminiPro.cpython-312.pyc
gskChat/Provider/__pycache__/GeminiProChat.cpython-312.pyc
gskChat/Provider/__pycache__/GigaChat.cpython-312.pyc
