Metadata-Version: 2.1
Name: gskChat
Version: 1.0.9
Summary: Gsk Chatbot
Author: tafik
Author-email: <doneld528@gmail.com>
Keywords: python,chatbot,reverse-engineering,openai,chatbots,gpt,language-model,gpt-3,gpt3,openai-api,gpt-4,gpt4,chatgpt,chatgpt-api,openai-chatgpt,chatgpt-free,chatgpt-4,chatgpt4,chatgpt4-api,free,free-gpt,gpt4free,g4f
Classifier: Development Status :: 2 - Pre-Alpha
Classifier: Intended Audience :: Developers
Classifier: Programming Language :: Python :: 3
Classifier: Operating System :: Unix
Classifier: Operating System :: MacOS :: MacOS X
Classifier: Operating System :: Microsoft :: Windows
Requires-Dist: requests
Requires-Dist: aiohttp
Requires-Dist: brotli
Provides-Extra: all
Requires-Dist: curl_cffi>=0.6.2; extra == "all"
Requires-Dist: certifi; extra == "all"
Requires-Dist: async-property; extra == "all"
Requires-Dist: py-arkose-generator; extra == "all"
Requires-Dist: browser_cookie3; extra == "all"
Requires-Dist: PyExecJS; extra == "all"
Requires-Dist: duckduckgo-search>=5.0; extra == "all"
Requires-Dist: beautifulsoup4; extra == "all"
Requires-Dist: brotli; extra == "all"
Requires-Dist: platformdirs; extra == "all"
Requires-Dist: undetected-chromedriver>=3.5.5; extra == "all"
Requires-Dist: setuptools; extra == "all"
Requires-Dist: aiohttp_socks; extra == "all"
Requires-Dist: pillow; extra == "all"
Requires-Dist: cairosvg; extra == "all"
Requires-Dist: werkzeug; extra == "all"
Requires-Dist: flask; extra == "all"
Requires-Dist: loguru; extra == "all"
Requires-Dist: fastapi; extra == "all"
Requires-Dist: uvicorn; extra == "all"
Requires-Dist: nest_asyncio; extra == "all"
Requires-Dist: selenium-wire; extra == "all"
Provides-Extra: image
Requires-Dist: pillow; extra == "image"
Requires-Dist: cairosvg; extra == "image"
Requires-Dist: beautifulsoup4; extra == "image"
Provides-Extra: webdriver
Requires-Dist: platformdirs; extra == "webdriver"
Requires-Dist: undetected-chromedriver; extra == "webdriver"
Requires-Dist: setuptools; extra == "webdriver"
Requires-Dist: selenium-wire; extra == "webdriver"
Provides-Extra: openai
Requires-Dist: async-property; extra == "openai"
Requires-Dist: py-arkose-generator; extra == "openai"
Requires-Dist: brotli; extra == "openai"
Provides-Extra: api
Requires-Dist: loguru; extra == "api"
Requires-Dist: fastapi; extra == "api"
Requires-Dist: uvicorn; extra == "api"
Requires-Dist: nest_asyncio; extra == "api"
Provides-Extra: gui
Requires-Dist: werkzeug; extra == "gui"
Requires-Dist: flask; extra == "gui"
Requires-Dist: beautifulsoup4; extra == "gui"
Requires-Dist: pillow; extra == "gui"
Requires-Dist: duckduckgo-search>=5.0; extra == "gui"
Requires-Dist: browser_cookie3; extra == "gui"
Provides-Extra: local
Requires-Dist: gpt4all; extra == "local"
